{
  "basics": {
    "name": "Yinsheng Zhang",
    "email": "oo@zju.edu.cn",
    "phone": "",
    "website": "https://zys.github.io",
    "summary": "Researcher on Data Science and Aritificial Intelligence",
    "location": {
      "address": "18 Xuezheng Street, Qiantang District",
      "postalCode": "",
      "city": "Hangzhou",
      "countryCode": "CN",
      "region": ""
    },
    "profiles": [
      {
        "network": "Web of Science",
        "username": "",
        "url": "https://www.webofscience.com/wos/author/record/HGC-3039-2022"
      },
      {
        "network": "ORCID",
        "username": "",
        "url": "https://orcid.org/0000-0003-4971-8809"
      },
      {
        "network": "GitHub",
        "username": "zhangys11",
        "url": "https://github.com/zhangys11"
      }
    ]
  },
  "work": [],
  "education": [
    {
      "institution": "Zhejiang University",
      "area": "Ph.D in BME",
      "studyType": "",
      "startDate": "",
      "endDate": "2015",
      "gpa": null,
      "courses": []
    },
    {
      "institution": "Zhejiang University",
      "area": "M.S. in BME",
      "studyType": "",
      "startDate": "",
      "endDate": "2008",
      "gpa": null,
      "courses": []
    }
  ],
  "skills": [],
  "languages": [],
  "interests": [],
  "references": []
}
